huaweicloudsdkaom/__init__.py
huaweicloudsdkaom/v1/__init__.py
huaweicloudsdkaom/v1/aom_async_client.py
huaweicloudsdkaom/v1/aom_client.py
huaweicloudsdkaom/v1/model/__init__.py
huaweicloudsdkaom/v1/model/approve_info.py
huaweicloudsdkaom/v1/model/create_workflow_request.py
huaweicloudsdkaom/v1/model/create_workflow_response.py
huaweicloudsdkaom/v1/model/execute_workflow_request.py
huaweicloudsdkaom/v1/model/execute_workflow_response.py
huaweicloudsdkaom/v1/model/execution_result_list.py
huaweicloudsdkaom/v1/model/job.py
huaweicloudsdkaom/v1/model/list_all_job_by_name_request.py
huaweicloudsdkaom/v1/model/list_all_job_by_name_response.py
huaweicloudsdkaom/v1/model/list_all_script_by_name_request.py
huaweicloudsdkaom/v1/model/list_all_script_by_name_response.py
huaweicloudsdkaom/v1/model/list_all_version_by_version_id_request.py
huaweicloudsdkaom/v1/model/list_all_version_by_version_id_response.py
huaweicloudsdkaom/v1/model/list_template_by_job_id_request.py
huaweicloudsdkaom/v1/model/list_template_by_job_id_request_body.py
huaweicloudsdkaom/v1/model/list_template_by_job_id_response.py
huaweicloudsdkaom/v1/model/list_workflow_executions_request.py
huaweicloudsdkaom/v1/model/list_workflow_executions_response.py
huaweicloudsdkaom/v1/model/list_workflow_request.py
huaweicloudsdkaom/v1/model/list_workflow_response.py
huaweicloudsdkaom/v1/model/metadata.py
huaweicloudsdkaom/v1/model/node.py
huaweicloudsdkaom/v1/model/parameter.py
huaweicloudsdkaom/v1/model/rate_control.py
huaweicloudsdkaom/v1/model/reference_info.py
huaweicloudsdkaom/v1/model/script.py
huaweicloudsdkaom/v1/model/script_version.py
huaweicloudsdkaom/v1/model/search_jobs_request_body.py
huaweicloudsdkaom/v1/model/search_scripts_request_body.py
huaweicloudsdkaom/v1/model/search_template_by_id_request.py
huaweicloudsdkaom/v1/model/search_template_by_id_response.py
huaweicloudsdkaom/v1/model/search_workflow_execution_detail_request.py
huaweicloudsdkaom/v1/model/search_workflow_execution_detail_response.py
huaweicloudsdkaom-3.1.184.dist-info/METADATA
huaweicloudsdkaom-3.1.184.dist-info/WHEEL
huaweicloudsdkaom-3.1.184.dist-info/licenses/LICENSE
huaweicloudsdkaom-3.1.184.dist-info/RECORD
